README.rst
setup.py
PdifFinder/Getpdifmoduleseq.py
PdifFinder/__init__.py
PdifFinder/angularPlasmid.py
PdifFinder/echarts.py
PdifFinder/pdifFinder.py
PdifFinder/pdifmodulecharts.py
PdifFinder.egg-info/PKG-INFO
PdifFinder.egg-info/SOURCES.txt
PdifFinder.egg-info/dependency_links.txt
PdifFinder.egg-info/entry_points.txt
PdifFinder.egg-info/requires.txt
PdifFinder.egg-info/top_level.txt
PdifFinder/AMRDB/sequences.fasta
PdifFinder/AMRDB/sequences.ndb
PdifFinder/AMRDB/sequences.nhr
PdifFinder/AMRDB/sequences.nin
PdifFinder/AMRDB/sequences.not
PdifFinder/AMRDB/sequences.nsq
PdifFinder/AMRDB/sequences.ntf
PdifFinder/AMRDB/sequences.nto
PdifFinder/data/genecolor.txt
PdifFinder/data/pdifdatabase.fasta
PdifFinder/data/redundant.seed.fa